fperms_iscore/__init__.py
fperms_iscore/apps.py
fperms_iscore/conf.py
fperms_iscore/enums.py
fperms_iscore/forms.py
fperms_iscore/main.py
fperms_iscore/mixins.py
fperms_iscore/permissions.py
fperms_iscore/locale/cs/LC_MESSAGES/django.mo
fperms_iscore/locale/cs/LC_MESSAGES/django.po
fperms_iscore/management/__init__.py
fperms_iscore/management/commands/__init__.py
fperms_iscore/management/commands/sync_permissions.py
skip_django_fperms_iscore-0.3.0.dist-info/AUTHORS.rst
skip_django_fperms_iscore-0.3.0.dist-info/LICENSE
skip_django_fperms_iscore-0.3.0.dist-info/METADATA
skip_django_fperms_iscore-0.3.0.dist-info/WHEEL
skip_django_fperms_iscore-0.3.0.dist-info/top_level.txt
skip_django_fperms_iscore-0.3.0.dist-info/RECORD
