Metadata-Version: 2.1
Name: skip-django-fperms-iscore
Version: 0.3.0
Summary: Perms for iscore library 
Home-page: https://github.com/skip-pay/django-fperms-iscore
Download-URL: https://github.com/skip-pay/django-fperms-iscore/archive/0.3.0.tar.gz
Author: Petr Olah
Author-email: djangoguru@gmail.com
License: MIT
Keywords: django-fperms-iscore
Classifier: Development Status :: 3 - Alpha
Classifier: Framework :: Django
Classifier: Framework :: Django :: 1.11
Classifier: Framework :: Django :: 2.0
Classifier: Intended Audience :: Developers
Classifier: License :: OSI Approved :: BSD License
Classifier: Natural Language :: English
Classifier: Programming Language :: Python :: 3
Classifier: Programming Language :: Python :: 3.5
Classifier: Programming Language :: Python :: 3.6
License-File: LICENSE
License-File: AUTHORS.rst
Requires-Dist: django >=4.2
Requires-Dist: skip-django-fperms >=0.5.0
Requires-Dist: skip-django-is-core >=2.25.0
